{
	"name": "MainCharacter",
	"plugin-id": "Sprite",
	"sid": 967065860454622,
	"isGlobal": false,
	"instanceVariables": [],
	"behaviorTypes": [
		{
			"behaviorId": "Platform",
			"name": "Platform",
			"sid": 552994685720876
		}
	],
	"effectTypes": [],
	"animations": {
		"items": [
			{
				"frames": [
					{
						"width": 540,
						"height": 540,
						"originX": 0.5,
						"originY": 0.5,
						"originalSource": "",
						"exportFormat": "png",
						"exportQuality": 0.8,
						"imageSpriteId": 2665067,
						"collisionPoly": {
							"points": [
								0.39444444444444443,
								0.39444444444444443,
								0.5,
								0.26666666666666666,
								0.6796296296296296,
								0.31851851851851853,
								0.6240740740740741,
								0.5,
								0.6833333333333332,
								0.701851851851852,
								0.4037037037037037,
								0.6981481481481481,
								0.34074074074074073,
								0.6574074074074074,
								0.5037037037037037,
								0.5
							]
						},
						"useCollisionPoly": true,
						"duration": 1
					},
					{
						"width": 540,
						"height": 540,
						"originX": 0.5,
						"originY": 0.5,
						"originalSource": "",
						"exportFormat": "png",
						"exportQuality": 0.8,
						"imageSpriteId": 5496756,
						"collisionPoly": {
							"points": [
								0.39444444444444443,
								0.39444444444444443,
								0.5,
								0.26666666666666666,
								0.6796296296296296,
								0.31851851851851853,
								0.6240740740740741,
								0.5,
								0.6833333333333332,
								0.701851851851852,
								0.4037037037037037,
								0.6981481481481481,
								0.34074074074074073,
								0.6574074074074074,
								0.5037037037037037,
								0.5
							]
						},
						"useCollisionPoly": true,
						"duration": 1
					},
					{
						"width": 540,
						"height": 540,
						"originX": 0.5,
						"originY": 0.5,
						"originalSource": "",
						"exportFormat": "png",
						"exportQuality": 0.8,
						"imageSpriteId": 3496236,
						"collisionPoly": {
							"points": [
								0.39444444444444443,
								0.39444444444444443,
								0.5,
								0.26666666666666666,
								0.6796296296296296,
								0.31851851851851853,
								0.6240740740740741,
								0.5,
								0.6833333333333332,
								0.701851851851852,
								0.4037037037037037,
								0.6981481481481481,
								0.34074074074074073,
								0.6574074074074074,
								0.5037037037037037,
								0.5
							]
						},
						"useCollisionPoly": true,
						"duration": 1
					},
					{
						"width": 540,
						"height": 540,
						"originX": 0.5,
						"originY": 0.5,
						"originalSource": "",
						"exportFormat": "png",
						"exportQuality": 0.8,
						"imageSpriteId": 3886862,
						"collisionPoly": {
							"points": [
								0.39444444444444443,
								0.39444444444444443,
								0.5,
								0.26666666666666666,
								0.6796296296296296,
								0.31851851851851853,
								0.6240740740740741,
								0.5,
								0.6833333333333332,
								0.701851851851852,
								0.4037037037037037,
								0.6981481481481481,
								0.34074074074074073,
								0.6574074074074074,
								0.5037037037037037,
								0.5
							]
						},
						"useCollisionPoly": true,
						"duration": 1
					},
					{
						"width": 540,
						"height": 540,
						"originX": 0.5,
						"originY": 0.5,
						"originalSource": "",
						"exportFormat": "png",
						"exportQuality": 0.8,
						"imageSpriteId": 5960791,
						"collisionPoly": {
							"points": [
								0.39444444444444443,
								0.39444444444444443,
								0.5,
								0.26666666666666666,
								0.6796296296296296,
								0.31851851851851853,
								0.6240740740740741,
								0.5,
								0.6833333333333332,
								0.701851851851852,
								0.4037037037037037,
								0.6981481481481481,
								0.34074074074074073,
								0.6574074074074074,
								0.5037037037037037,
								0.5
							]
						},
						"useCollisionPoly": true,
						"duration": 1
					},
					{
						"width": 540,
						"height": 540,
						"originX": 0.5,
						"originY": 0.5,
						"originalSource": "",
						"exportFormat": "png",
						"exportQuality": 0.8,
						"imageSpriteId": 5511000,
						"collisionPoly": {
							"points": [
								0.39444444444444443,
								0.39444444444444443,
								0.5,
								0.26666666666666666,
								0.6796296296296296,
								0.31851851851851853,
								0.6240740740740741,
								0.5,
								0.6833333333333332,
								0.701851851851852,
								0.4037037037037037,
								0.6981481481481481,
								0.34074074074074073,
								0.6574074074074074,
								0.5037037037037037,
								0.5
							]
						},
						"useCollisionPoly": true,
						"duration": 1
					}
				],
				"sid": 774155328635485,
				"name": "Idle",
				"isLooping": true,
				"isPingPong": false,
				"repeatCount": 1,
				"repeatTo": 0,
				"speed": 14
			},
			{
				"frames": [
					{
						"width": 540,
						"height": 540,
						"originX": 0.5,
						"originY": 0.5,
						"originalSource": "",
						"exportFormat": "png",
						"exportQuality": 0.8,
						"imageSpriteId": 3203863,
						"collisionPoly": {
							"points": [
								0.39444444444444443,
								0.39444444444444443,
								0.5,
								0.26666666666666666,
								0.6796296296296296,
								0.31851851851851853,
								0.6240740740740741,
								0.5,
								0.6833333333333332,
								0.701851851851852,
								0.4037037037037037,
								0.6981481481481481,
								0.34074074074074073,
								0.6574074074074074,
								0.5037037037037037,
								0.5
							]
						},
						"useCollisionPoly": true,
						"duration": 1
					},
					{
						"width": 540,
						"height": 540,
						"originX": 0.5,
						"originY": 0.5,
						"originalSource": "",
						"exportFormat": "png",
						"exportQuality": 0.8,
						"imageSpriteId": 7744702,
						"collisionPoly": {
							"points": [
								0.39444444444444443,
								0.39444444444444443,
								0.5,
								0.26666666666666666,
								0.6796296296296296,
								0.31851851851851853,
								0.6240740740740741,
								0.5,
								0.6833333333333332,
								0.701851851851852,
								0.4037037037037037,
								0.6981481481481481,
								0.34074074074074073,
								0.6574074074074074,
								0.5037037037037037,
								0.5
							]
						},
						"useCollisionPoly": true,
						"duration": 1
					},
					{
						"width": 540,
						"height": 540,
						"originX": 0.5,
						"originY": 0.5,
						"originalSource": "",
						"exportFormat": "png",
						"exportQuality": 0.8,
						"imageSpriteId": 6594876,
						"collisionPoly": {
							"points": [
								0.39444444444444443,
								0.39444444444444443,
								0.5,
								0.26666666666666666,
								0.6796296296296296,
								0.31851851851851853,
								0.6240740740740741,
								0.5,
								0.6833333333333332,
								0.701851851851852,
								0.4037037037037037,
								0.6981481481481481,
								0.34074074074074073,
								0.6574074074074074,
								0.5037037037037037,
								0.5
							]
						},
						"useCollisionPoly": true,
						"duration": 1
					}
				],
				"sid": 889677807970191,
				"name": "Turn",
				"isLooping": false,
				"isPingPong": false,
				"repeatCount": 1,
				"repeatTo": 0,
				"speed": 14
			},
			{
				"frames": [
					{
						"width": 540,
						"height": 540,
						"originX": 0.5,
						"originY": 0.5,
						"originalSource": "",
						"exportFormat": "png",
						"exportQuality": 0.8,
						"imageSpriteId": 3199441,
						"collisionPoly": {
							"points": [
								0.39444444444444443,
								0.39444444444444443,
								0.5,
								0.26666666666666666,
								0.6796296296296296,
								0.31851851851851853,
								0.6240740740740741,
								0.5,
								0.6833333333333332,
								0.701851851851852,
								0.4037037037037037,
								0.6981481481481481,
								0.34074074074074073,
								0.6574074074074074,
								0.5037037037037037,
								0.5
							]
						},
						"useCollisionPoly": true,
						"duration": 1
					},
					{
						"width": 540,
						"height": 540,
						"originX": 0.5,
						"originY": 0.5,
						"originalSource": "",
						"exportFormat": "png",
						"exportQuality": 0.8,
						"imageSpriteId": 2631924,
						"collisionPoly": {
							"points": [
								0.39444444444444443,
								0.39444444444444443,
								0.5,
								0.26666666666666666,
								0.6796296296296296,
								0.31851851851851853,
								0.6240740740740741,
								0.5,
								0.6833333333333332,
								0.701851851851852,
								0.4037037037037037,
								0.6981481481481481,
								0.34074074074074073,
								0.6574074074074074,
								0.5037037037037037,
								0.5
							]
						},
						"useCollisionPoly": true,
						"duration": 1
					},
					{
						"width": 540,
						"height": 540,
						"originX": 0.5,
						"originY": 0.5,
						"originalSource": "",
						"exportFormat": "png",
						"exportQuality": 0.8,
						"imageSpriteId": 1909840,
						"collisionPoly": {
							"points": [
								0.39444444444444443,
								0.39444444444444443,
								0.5,
								0.26666666666666666,
								0.6796296296296296,
								0.31851851851851853,
								0.6240740740740741,
								0.5,
								0.6833333333333332,
								0.701851851851852,
								0.4037037037037037,
								0.6981481481481481,
								0.34074074074074073,
								0.6574074074074074,
								0.5037037037037037,
								0.5
							]
						},
						"useCollisionPoly": true,
						"duration": 1
					}
				],
				"sid": 331351031723361,
				"name": "Turn 2",
				"isLooping": false,
				"isPingPong": false,
				"repeatCount": 1,
				"repeatTo": 0,
				"speed": 14
			},
			{
				"frames": [
					{
						"width": 540,
						"height": 540,
						"originX": 0.5,
						"originY": 0.5,
						"originalSource": "",
						"exportFormat": "png",
						"exportQuality": 0.8,
						"imageSpriteId": 2368336,
						"collisionPoly": {
							"points": [
								0.39444444444444443,
								0.39444444444444443,
								0.5,
								0.26666666666666666,
								0.6796296296296296,
								0.31851851851851853,
								0.6240740740740741,
								0.5,
								0.6833333333333332,
								0.701851851851852,
								0.4037037037037037,
								0.6981481481481481,
								0.34074074074074073,
								0.6574074074074074,
								0.5037037037037037,
								0.5
							]
						},
						"useCollisionPoly": true,
						"duration": 1
					},
					{
						"width": 540,
						"height": 540,
						"originX": 0.5,
						"originY": 0.5,
						"originalSource": "",
						"exportFormat": "png",
						"exportQuality": 0.8,
						"imageSpriteId": 421030,
						"collisionPoly": {
							"points": [
								0.39444444444444443,
								0.39444444444444443,
								0.5,
								0.26666666666666666,
								0.6796296296296296,
								0.31851851851851853,
								0.6240740740740741,
								0.5,
								0.6833333333333332,
								0.701851851851852,
								0.4037037037037037,
								0.6981481481481481,
								0.34074074074074073,
								0.6574074074074074,
								0.5037037037037037,
								0.5
							]
						},
						"useCollisionPoly": true,
						"duration": 1
					},
					{
						"width": 540,
						"height": 540,
						"originX": 0.5,
						"originY": 0.5,
						"originalSource": "",
						"exportFormat": "png",
						"exportQuality": 0.8,
						"imageSpriteId": 622244,
						"collisionPoly": {
							"points": [
								0.39444444444444443,
								0.39444444444444443,
								0.5,
								0.26666666666666666,
								0.6796296296296296,
								0.31851851851851853,
								0.6240740740740741,
								0.5,
								0.6833333333333332,
								0.701851851851852,
								0.4037037037037037,
								0.6981481481481481,
								0.34074074074074073,
								0.6574074074074074,
								0.5037037037037037,
								0.5
							]
						},
						"useCollisionPoly": true,
						"duration": 1
					},
					{
						"width": 540,
						"height": 540,
						"originX": 0.5,
						"originY": 0.5,
						"originalSource": "",
						"exportFormat": "png",
						"exportQuality": 0.8,
						"imageSpriteId": 6644501,
						"collisionPoly": {
							"points": [
								0.39444444444444443,
								0.39444444444444443,
								0.5,
								0.26666666666666666,
								0.6796296296296296,
								0.31851851851851853,
								0.6240740740740741,
								0.5,
								0.6833333333333332,
								0.701851851851852,
								0.4037037037037037,
								0.6981481481481481,
								0.34074074074074073,
								0.6574074074074074,
								0.5037037037037037,
								0.5
							]
						},
						"useCollisionPoly": true,
						"duration": 1
					},
					{
						"width": 540,
						"height": 540,
						"originX": 0.5,
						"originY": 0.5,
						"originalSource": "",
						"exportFormat": "png",
						"exportQuality": 0.8,
						"imageSpriteId": 273938,
						"collisionPoly": {
							"points": [
								0.39444444444444443,
								0.39444444444444443,
								0.5,
								0.26666666666666666,
								0.6796296296296296,
								0.31851851851851853,
								0.6240740740740741,
								0.5,
								0.6833333333333332,
								0.701851851851852,
								0.4037037037037037,
								0.6981481481481481,
								0.34074074074074073,
								0.6574074074074074,
								0.5037037037037037,
								0.5
							]
						},
						"useCollisionPoly": true,
						"duration": 1
					},
					{
						"width": 540,
						"height": 540,
						"originX": 0.5,
						"originY": 0.5,
						"originalSource": "",
						"exportFormat": "png",
						"exportQuality": 0.8,
						"imageSpriteId": 7452420,
						"collisionPoly": {
							"points": [
								0.39444444444444443,
								0.39444444444444443,
								0.5,
								0.26666666666666666,
								0.6796296296296296,
								0.31851851851851853,
								0.6240740740740741,
								0.5,
								0.6833333333333332,
								0.701851851851852,
								0.4037037037037037,
								0.6981481481481481,
								0.34074074074074073,
								0.6574074074074074,
								0.5037037037037037,
								0.5
							]
						},
						"useCollisionPoly": true,
						"duration": 1
					}
				],
				"sid": 450201852253888,
				"name": "Walk",
				"isLooping": true,
				"isPingPong": false,
				"repeatCount": 1,
				"repeatTo": 0,
				"speed": 12
			},
			{
				"frames": [
					{
						"width": 540,
						"height": 540,
						"originX": 0.5,
						"originY": 0.5,
						"originalSource": "",
						"exportFormat": "png",
						"exportQuality": 0.8,
						"imageSpriteId": 3811611,
						"collisionPoly": {
							"points": [
								0.39444444444444443,
								0.39444444444444443,
								0.5,
								0.26666666666666666,
								0.6796296296296296,
								0.31851851851851853,
								0.6240740740740741,
								0.5,
								0.6833333333333332,
								0.701851851851852,
								0.4037037037037037,
								0.6981481481481481,
								0.34074074074074073,
								0.6574074074074074,
								0.5037037037037037,
								0.5
							]
						},
						"useCollisionPoly": true,
						"duration": 1
					}
				],
				"sid": 987050132172553,
				"name": "Idle to Run",
				"isLooping": false,
				"isPingPong": false,
				"repeatCount": 1,
				"repeatTo": 0,
				"speed": 14
			},
			{
				"frames": [
					{
						"width": 540,
						"height": 540,
						"originX": 0.5,
						"originY": 0.5,
						"originalSource": "",
						"exportFormat": "png",
						"exportQuality": 0.8,
						"imageSpriteId": 3178683,
						"collisionPoly": {
							"points": [
								0.39444444444444443,
								0.39444444444444443,
								0.5,
								0.26666666666666666,
								0.6796296296296296,
								0.31851851851851853,
								0.6240740740740741,
								0.5,
								0.6833333333333332,
								0.701851851851852,
								0.4037037037037037,
								0.6981481481481481,
								0.34074074074074073,
								0.6574074074074074,
								0.5037037037037037,
								0.5
							]
						},
						"useCollisionPoly": true,
						"duration": 1
					},
					{
						"width": 540,
						"height": 540,
						"originX": 0.5,
						"originY": 0.5,
						"originalSource": "",
						"exportFormat": "png",
						"exportQuality": 0.8,
						"imageSpriteId": 9499732,
						"collisionPoly": {
							"points": [
								0.39444444444444443,
								0.39444444444444443,
								0.5,
								0.26666666666666666,
								0.6796296296296296,
								0.31851851851851853,
								0.6240740740740741,
								0.5,
								0.6833333333333332,
								0.701851851851852,
								0.4037037037037037,
								0.6981481481481481,
								0.34074074074074073,
								0.6574074074074074,
								0.5037037037037037,
								0.5
							]
						},
						"useCollisionPoly": true,
						"duration": 1
					},
					{
						"width": 540,
						"height": 540,
						"originX": 0.5,
						"originY": 0.5,
						"originalSource": "",
						"exportFormat": "png",
						"exportQuality": 0.8,
						"imageSpriteId": 2129951,
						"collisionPoly": {
							"points": [
								0.39444444444444443,
								0.39444444444444443,
								0.5,
								0.26666666666666666,
								0.6796296296296296,
								0.31851851851851853,
								0.6240740740740741,
								0.5,
								0.6833333333333332,
								0.701851851851852,
								0.4037037037037037,
								0.6981481481481481,
								0.34074074074074073,
								0.6574074074074074,
								0.5037037037037037,
								0.5
							]
						},
						"useCollisionPoly": true,
						"duration": 1
					},
					{
						"width": 540,
						"height": 540,
						"originX": 0.5,
						"originY": 0.5,
						"originalSource": "",
						"exportFormat": "png",
						"exportQuality": 0.8,
						"imageSpriteId": 9014559,
						"collisionPoly": {
							"points": [
								0.39444444444444443,
								0.39444444444444443,
								0.5,
								0.26666666666666666,
								0.6796296296296296,
								0.31851851851851853,
								0.6240740740740741,
								0.5,
								0.6833333333333332,
								0.701851851851852,
								0.4037037037037037,
								0.6981481481481481,
								0.34074074074074073,
								0.6574074074074074,
								0.5037037037037037,
								0.5
							]
						},
						"useCollisionPoly": true,
						"duration": 1
					}
				],
				"sid": 745823107298469,
				"name": "Run",
				"isLooping": true,
				"isPingPong": false,
				"repeatCount": 1,
				"repeatTo": 0,
				"speed": 14
			},
			{
				"frames": [
					{
						"width": 540,
						"height": 540,
						"originX": 0.5,
						"originY": 0.5,
						"originalSource": "",
						"exportFormat": "png",
						"exportQuality": 0.8,
						"imageSpriteId": 7080814,
						"collisionPoly": {
							"points": [
								0.39444444444444443,
								0.39444444444444443,
								0.5,
								0.26666666666666666,
								0.6796296296296296,
								0.31851851851851853,
								0.6240740740740741,
								0.5,
								0.6833333333333332,
								0.701851851851852,
								0.4037037037037037,
								0.6981481481481481,
								0.34074074074074073,
								0.6574074074074074,
								0.5037037037037037,
								0.5
							]
						},
						"useCollisionPoly": true,
						"duration": 1
					}
				],
				"sid": 424492840803226,
				"name": "Run to Idle",
				"isLooping": false,
				"isPingPong": false,
				"repeatCount": 1,
				"repeatTo": 0,
				"speed": 14
			},
			{
				"frames": [
					{
						"width": 540,
						"height": 540,
						"originX": 0.5,
						"originY": 0.5,
						"originalSource": "",
						"exportFormat": "png",
						"exportQuality": 0.8,
						"imageSpriteId": 5256996,
						"collisionPoly": {
							"points": [
								0.2592592592592591,
								0.2666666666666665,
								0.5,
								0.2833333333333333,
								0.7296296296296296,
								0.26851851851851855,
								0.9,
								0.5,
								0.7407407407407407,
								0.7407407407407407,
								0.2481481481481479,
								0.7333333333333333,
								0.17962962962962956,
								0.6185185185185186,
								0.12407407407407411,
								0.4259259259259258
							]
						},
						"useCollisionPoly": true,
						"duration": 1
					},
					{
						"width": 540,
						"height": 540,
						"originX": 0.5,
						"originY": 0.5,
						"originalSource": "",
						"exportFormat": "png",
						"exportQuality": 0.8,
						"imageSpriteId": 6565018,
						"collisionPoly": {
							"points": [
								0.2592592592592591,
								0.2666666666666665,
								0.5,
								0.2833333333333333,
								0.7296296296296296,
								0.26851851851851855,
								0.9,
								0.5,
								0.7407407407407407,
								0.7407407407407407,
								0.2481481481481479,
								0.7333333333333333,
								0.17962962962962956,
								0.6185185185185186,
								0.12407407407407411,
								0.4259259259259258
							]
						},
						"useCollisionPoly": true,
						"duration": 1
					},
					{
						"width": 540,
						"height": 540,
						"originX": 0.5,
						"originY": 0.5,
						"originalSource": "",
						"exportFormat": "png",
						"exportQuality": 0.8,
						"imageSpriteId": 3576237,
						"collisionPoly": {
							"points": [
								0.2592592592592591,
								0.2666666666666665,
								0.5,
								0.2833333333333333,
								0.7296296296296296,
								0.26851851851851855,
								0.9,
								0.5,
								0.7407407407407407,
								0.7407407407407407,
								0.2481481481481479,
								0.7333333333333333,
								0.17962962962962956,
								0.6185185185185186,
								0.12407407407407411,
								0.4259259259259258
							]
						},
						"useCollisionPoly": true,
						"duration": 1
					},
					{
						"width": 540,
						"height": 540,
						"originX": 0.5,
						"originY": 0.5,
						"originalSource": "",
						"exportFormat": "png",
						"exportQuality": 0.8,
						"imageSpriteId": 1816179,
						"collisionPoly": {
							"points": [
								0.2592592592592591,
								0.2666666666666665,
								0.5,
								0.2833333333333333,
								0.7296296296296296,
								0.26851851851851855,
								0.9,
								0.5,
								0.7407407407407407,
								0.7407407407407407,
								0.2481481481481479,
								0.7333333333333333,
								0.17962962962962956,
								0.6185185185185186,
								0.12407407407407411,
								0.4259259259259258
							]
						},
						"useCollisionPoly": true,
						"duration": 1
					},
					{
						"width": 540,
						"height": 540,
						"originX": 0.5,
						"originY": 0.5,
						"originalSource": "",
						"exportFormat": "png",
						"exportQuality": 0.8,
						"imageSpriteId": 9024973,
						"collisionPoly": {
							"points": [
								0.2592592592592591,
								0.2666666666666665,
								0.5,
								0.2833333333333333,
								0.7296296296296296,
								0.26851851851851855,
								0.9,
								0.5,
								0.7407407407407407,
								0.7407407407407407,
								0.2481481481481479,
								0.7333333333333333,
								0.17962962962962956,
								0.6185185185185186,
								0.12407407407407411,
								0.4259259259259258
							]
						},
						"useCollisionPoly": true,
						"duration": 1
					},
					{
						"width": 540,
						"height": 540,
						"originX": 0.5,
						"originY": 0.5,
						"originalSource": "",
						"exportFormat": "png",
						"exportQuality": 0.8,
						"imageSpriteId": 4627507,
						"collisionPoly": {
							"points": [
								0.2592592592592591,
								0.2666666666666665,
								0.5,
								0.2833333333333333,
								0.7296296296296296,
								0.26851851851851855,
								0.9,
								0.5,
								0.7407407407407407,
								0.7407407407407407,
								0.2481481481481479,
								0.7333333333333333,
								0.17962962962962956,
								0.6185185185185186,
								0.12407407407407411,
								0.4259259259259258
							]
						},
						"useCollisionPoly": true,
						"duration": 1
					},
					{
						"width": 540,
						"height": 540,
						"originX": 0.5,
						"originY": 0.5,
						"originalSource": "",
						"exportFormat": "png",
						"exportQuality": 0.8,
						"imageSpriteId": 9762419,
						"collisionPoly": {
							"points": [
								0.2592592592592591,
								0.2666666666666665,
								0.5,
								0.2833333333333333,
								0.7296296296296296,
								0.26851851851851855,
								0.9,
								0.5,
								0.7407407407407407,
								0.7407407407407407,
								0.2481481481481479,
								0.7333333333333333,
								0.17962962962962956,
								0.6185185185185186,
								0.12407407407407411,
								0.4259259259259258
							]
						},
						"useCollisionPoly": true,
						"duration": 1
					},
					{
						"width": 540,
						"height": 540,
						"originX": 0.5,
						"originY": 0.5,
						"originalSource": "",
						"exportFormat": "png",
						"exportQuality": 0.8,
						"imageSpriteId": 4788234,
						"collisionPoly": {
							"points": [
								0.2592592592592591,
								0.2666666666666665,
								0.5,
								0.2833333333333333,
								0.7296296296296296,
								0.26851851851851855,
								0.9,
								0.5,
								0.7407407407407407,
								0.7407407407407407,
								0.2481481481481479,
								0.7333333333333333,
								0.17962962962962956,
								0.6185185185185186,
								0.12407407407407411,
								0.4259259259259258
							]
						},
						"useCollisionPoly": true,
						"duration": 1
					}
				],
				"sid": 501112892552731,
				"name": "Dash Attack",
				"isLooping": false,
				"isPingPong": false,
				"repeatCount": 1,
				"repeatTo": 0,
				"speed": 14
			},
			{
				"frames": [
					{
						"width": 540,
						"height": 540,
						"originX": 0.5,
						"originY": 0.5,
						"originalSource": "",
						"exportFormat": "png",
						"exportQuality": 0.8,
						"imageSpriteId": 5622950,
						"collisionPoly": {
							"points": [
								0.46296296296296297,
								0.46296296296296297,
								0.5,
								0.3277777777777778,
								0.6851851851851852,
								0.31296296296296294,
								0.6370370370370371,
								0.5,
								0.6907407407407408,
								0.6907407407407408,
								0.37407407407407395,
								0.6907407407407407,
								0.3907407407407407,
								0.6074074074074074,
								0.2833333333333333,
								0.5
							]
						},
						"useCollisionPoly": true,
						"duration": 1
					},
					{
						"width": 540,
						"height": 540,
						"originX": 0.5,
						"originY": 0.5,
						"originalSource": "",
						"exportFormat": "png",
						"exportQuality": 0.8,
						"imageSpriteId": 7857721,
						"collisionPoly": {
							"points": [
								0.43148148148148147,
								0.43148148148148147,
								0.5,
								0.16666666666666666,
								0.6185185185185185,
								0.37962962962962965,
								0.6222222222222222,
								0.5,
								0.5962962962962963,
								0.5962962962962963,
								0.5,
								0.6277777777777778,
								0.46111111111111114,
								0.5370370370370371,
								0.3592592592592593,
								0.5
							]
						},
						"useCollisionPoly": true,
						"duration": 1
					}
				],
				"sid": 308074794584447,
				"name": "Idle to Jump",
				"isLooping": false,
				"isPingPong": false,
				"repeatCount": 1,
				"repeatTo": 0,
				"speed": 14
			},
			{
				"frames": [
					{
						"width": 540,
						"height": 540,
						"originX": 0.5,
						"originY": 0.5,
						"originalSource": "",
						"exportFormat": "png",
						"exportQuality": 0.8,
						"imageSpriteId": 6728093,
						"collisionPoly": {
							"points": [
								0.3907407407407407,
								0.3907407407407407,
								0.5,
								0.17407407407407408,
								0.6407407407407407,
								0.3574074074074074,
								0.6240740740740741,
								0.5,
								0.5981481481481481,
								0.5981481481481481,
								0.5,
								0.5981481481481481,
								0.362962962962963,
								0.6351851851851852,
								0.4425925925925926,
								0.5
							]
						},
						"useCollisionPoly": true,
						"duration": 1
					},
					{
						"width": 540,
						"height": 540,
						"originX": 0.5,
						"originY": 0.5,
						"originalSource": "",
						"exportFormat": "png",
						"exportQuality": 0.8,
						"imageSpriteId": 6814630,
						"collisionPoly": {
							"points": [
								0.3925925925925926,
								0.3925925925925926,
								0.5,
								0.17407407407407408,
								0.6407407407407407,
								0.3574074074074074,
								0.6333333333333333,
								0.5,
								0.5981481481481481,
								0.5981481481481481,
								0.5,
								0.5981481481481481,
								0.36666666666666664,
								0.6314814814814815,
								0.39444444444444443,
								0.5
							]
						},
						"useCollisionPoly": true,
						"duration": 1
					},
					{
						"width": 540,
						"height": 540,
						"originX": 0.5,
						"originY": 0.5,
						"originalSource": "",
						"exportFormat": "png",
						"exportQuality": 0.8,
						"imageSpriteId": 4801734,
						"collisionPoly": {
							"points": [
								0.42407407407407405,
								0.42407407407407405,
								0.5,
								0.17407407407407408,
								0.6407407407407407,
								0.3574074074074074,
								0.6370370370370371,
								0.5,
								0.5981481481481481,
								0.5981481481481481,
								0.5,
								0.5981481481481481,
								0.37777777777777777,
								0.6203703703703703,
								0.34074074074074073,
								0.5
							]
						},
						"useCollisionPoly": true,
						"duration": 1
					},
					{
						"width": 540,
						"height": 540,
						"originX": 0.5,
						"originY": 0.5,
						"originalSource": "",
						"exportFormat": "png",
						"exportQuality": 0.8,
						"imageSpriteId": 5212132,
						"collisionPoly": {
							"points": [
								0.39814814814814814,
								0.39814814814814814,
								0.5,
								0.17407407407407408,
								0.6407407407407407,
								0.3574074074074074,
								0.6277777777777778,
								0.5,
								0.5981481481481481,
								0.5981481481481481,
								0.5,
								0.5981481481481481,
								0.362962962962963,
								0.6351851851851852,
								0.3537037037037037,
								0.5
							]
						},
						"useCollisionPoly": true,
						"duration": 1
					}
				],
				"sid": 404109518515409,
				"name": "Jump",
				"isLooping": true,
				"isPingPong": false,
				"repeatCount": 1,
				"repeatTo": 0,
				"speed": 14
			},
			{
				"frames": [
					{
						"width": 540,
						"height": 540,
						"originX": 0.5,
						"originY": 0.5,
						"originalSource": "",
						"exportFormat": "png",
						"exportQuality": 0.8,
						"imageSpriteId": 5726090,
						"collisionPoly": {
							"points": [
								0.337037037037037,
								0.337037037037037,
								0.5,
								0.17777777777777778,
								0.6259259259259259,
								0.37222222222222223,
								0.6388888888888888,
								0.5,
								0.6111111111111112,
								0.6111111111111112,
								0.5,
								0.5814814814814815,
								0.4703703703703704,
								0.5277777777777778,
								0.2796296296296296,
								0.5
							]
						},
						"useCollisionPoly": true,
						"duration": 1
					},
					{
						"width": 540,
						"height": 540,
						"originX": 0.5,
						"originY": 0.5,
						"originalSource": "",
						"exportFormat": "png",
						"exportQuality": 0.8,
						"imageSpriteId": 8166534,
						"collisionPoly": {
							"points": [
								0.3333333333333333,
								0.3333333333333333,
								0.5,
								0.17222222222222222,
								0.7351851851851852,
								0.26296296296296295,
								0.6407407407407407,
								0.5,
								0.5851851851851851,
								0.5851851851851851,
								0.5,
								0.5925925925925926,
								0.4666666666666667,
								0.5314814814814814,
								0.42407407407407405,
								0.5
							]
						},
						"useCollisionPoly": true,
						"duration": 1
					}
				],
				"sid": 160034900379415,
				"name": "Jump to Fall",
				"isLooping": false,
				"isPingPong": false,
				"repeatCount": 1,
				"repeatTo": 0,
				"speed": 14
			},
			{
				"frames": [
					{
						"width": 540,
						"height": 540,
						"originX": 0.5,
						"originY": 0.5,
						"originalSource": "",
						"exportFormat": "png",
						"exportQuality": 0.8,
						"imageSpriteId": 5359646,
						"collisionPoly": {
							"points": [
								0.42407407407407405,
								0.42407407407407405,
								0.5,
								0.21481481481481482,
								0.7203703703703703,
								0.2777777777777778,
								0.6166666666666667,
								0.5,
								0.5666666666666667,
								0.5666666666666667,
								0.5,
								0.6018518518518519,
								0.4666666666666667,
								0.5314814814814814,
								0.3055555555555556,
								0.5
							]
						},
						"useCollisionPoly": true,
						"duration": 1
					},
					{
						"width": 540,
						"height": 540,
						"originX": 0.5,
						"originY": 0.5,
						"originalSource": "",
						"exportFormat": "png",
						"exportQuality": 0.8,
						"imageSpriteId": 5041649,
						"collisionPoly": {
							"points": [
								0.42407407407407405,
								0.42407407407407405,
								0.5,
								0.21481481481481482,
								0.7203703703703703,
								0.2777777777777778,
								0.6129629629629629,
								0.5,
								0.5666666666666667,
								0.5666666666666667,
								0.5,
								0.6018518518518519,
								0.4666666666666667,
								0.5314814814814814,
								0.3055555555555556,
								0.5
							]
						},
						"useCollisionPoly": true,
						"duration": 1
					},
					{
						"width": 540,
						"height": 540,
						"originX": 0.5,
						"originY": 0.5,
						"originalSource": "",
						"exportFormat": "png",
						"exportQuality": 0.8,
						"imageSpriteId": 1482562,
						"collisionPoly": {
							"points": [
								0.42407407407407405,
								0.42407407407407405,
								0.5,
								0.21481481481481482,
								0.7203703703703703,
								0.2777777777777778,
								0.6074074074074074,
								0.5,
								0.5666666666666667,
								0.5666666666666667,
								0.5,
								0.6018518518518519,
								0.4666666666666667,
								0.5314814814814814,
								0.3055555555555556,
								0.5
							]
						},
						"useCollisionPoly": true,
						"duration": 1
					}
				],
				"sid": 647314504382226,
				"name": "Fall",
				"isLooping": true,
				"isPingPong": false,
				"repeatCount": 1,
				"repeatTo": 0,
				"speed": 14
			},
			{
				"frames": [
					{
						"width": 540,
						"height": 540,
						"originX": 0.5,
						"originY": 0.5,
						"originalSource": "",
						"exportFormat": "png",
						"exportQuality": 0.8,
						"imageSpriteId": 56180,
						"collisionPoly": {
							"points": [
								0.3648148148148148,
								0.3648148148148148,
								0.5,
								0.30185185185185187,
								0.7,
								0.29814814814814816,
								0.7870370370370371,
								0.5,
								0.7185185185185184,
								0.6925925925925924,
								0.3444444444444445,
								0.6944444444444444,
								0.4185185185185185,
								0.5796296296296296,
								0.42592592592592593,
								0.5
							]
						},
						"useCollisionPoly": true,
						"duration": 1
					},
					{
						"width": 540,
						"height": 540,
						"originX": 0.5,
						"originY": 0.5,
						"originalSource": "",
						"exportFormat": "png",
						"exportQuality": 0.8,
						"imageSpriteId": 7126258,
						"collisionPoly": {
							"points": [
								0.43333333333333335,
								0.43333333333333335,
								0.5,
								0.3351851851851852,
								0.687037037037037,
								0.3111111111111111,
								0.725925925925926,
								0.5,
								0.7092592592592589,
								0.624074074074074,
								0.7074074074074067,
								0.6981481481481482,
								0.35555555555555557,
								0.6944444444444439,
								0.28888888888888886,
								0.5
							]
						},
						"useCollisionPoly": true,
						"duration": 1
					}
				],
				"sid": 168350953860880,
				"name": "Fall to Idle",
				"isLooping": false,
				"isPingPong": false,
				"repeatCount": 1,
				"repeatTo": 0,
				"speed": 14
			},
			{
				"frames": [
					{
						"width": 540,
						"height": 540,
						"originX": 0.5,
						"originY": 0.5,
						"originalSource": "",
						"exportFormat": "png",
						"exportQuality": 0.8,
						"imageSpriteId": 1505898,
						"collisionPoly": {
							"points": [
								0.3314814814814815,
								0.3314814814814815,
								0.5,
								0.22407407407407406,
								0.6685185185185185,
								0.3296296296296296,
								0.6685185185185185,
								0.5,
								0.5814814814814815,
								0.5814814814814815,
								0.5,
								0.7277777777777777,
								0.38333333333333336,
								0.6148148148148148,
								0.2740740740740741,
								0.5
							]
						},
						"useCollisionPoly": true,
						"duration": 1
					},
					{
						"width": 540,
						"height": 540,
						"originX": 0.5,
						"originY": 0.5,
						"originalSource": "",
						"exportFormat": "png",
						"exportQuality": 0.8,
						"imageSpriteId": 2604246,
						"collisionPoly": {
							"points": [
								0.2814814814814815,
								0.2814814814814815,
								0.5,
								0.21666666666666667,
								0.7129629629629629,
								0.2851851851851852,
								0.9351851851851852,
								0.5,
								0.5814814814814815,
								0.5814814814814815,
								0.5,
								0.7037037037037037,
								0.3814814814814815,
								0.6166666666666667,
								0.24259259259259258,
								0.5
							]
						},
						"useCollisionPoly": true,
						"duration": 1
					},
					{
						"width": 540,
						"height": 540,
						"originX": 0.5,
						"originY": 0.5,
						"originalSource": "",
						"exportFormat": "png",
						"exportQuality": 0.8,
						"imageSpriteId": 3958000,
						"collisionPoly": {
							"points": [
								0.38333333333333336,
								0.38333333333333336,
								0.5,
								0.2074074074074074,
								0.6388888888888888,
								0.3592592592592593,
								0.8444444444444444,
								0.5,
								0.5833333333333334,
								0.5833333333333334,
								0.5,
								0.6759259259259259,
								0.3648148148148148,
								0.6333333333333333,
								0.10185185185185185,
								0.5
							]
						},
						"useCollisionPoly": true,
						"duration": 1
					},
					{
						"width": 540,
						"height": 540,
						"originX": 0.5,
						"originY": 0.5,
						"originalSource": "",
						"exportFormat": "png",
						"exportQuality": 0.8,
						"imageSpriteId": 7444541,
						"collisionPoly": {
							"points": [
								0.31296296296296294,
								0.31296296296296294,
								0.5,
								0.2574074074074074,
								0.6314814814814815,
								0.36666666666666664,
								0.6240740740740741,
								0.5,
								0.5962962962962963,
								0.5962962962962963,
								0.5,
								0.6833333333333333,
								0.3962962962962963,
								0.6018518518518519,
								0.37777777777777777,
								0.5
							]
						},
						"useCollisionPoly": true,
						"duration": 1
					},
					{
						"width": 540,
						"height": 540,
						"originX": 0.5,
						"originY": 0.5,
						"originalSource": "",
						"exportFormat": "png",
						"exportQuality": 0.8,
						"imageSpriteId": 7902554,
						"collisionPoly": {
							"points": [
								0.3388888888888889,
								0.3388888888888889,
								0.5,
								0.26296296296296295,
								0.6462962962962963,
								0.35185185185185186,
								0.6,
								0.5,
								0.6,
								0.6,
								0.5,
								0.7166666666666667,
								0.40370370370370373,
								0.5944444444444444,
								0.2962962962962963,
								0.5
							]
						},
						"useCollisionPoly": true,
						"duration": 1
					}
				],
				"sid": 259115139133893,
				"name": "Jump Attack",
				"isLooping": false,
				"isPingPong": false,
				"repeatCount": 1,
				"repeatTo": 0,
				"speed": 14
			},
			{
				"frames": [
					{
						"width": 540,
						"height": 540,
						"originX": 0.5,
						"originY": 0.5,
						"originalSource": "",
						"exportFormat": "png",
						"exportQuality": 0.8,
						"imageSpriteId": 8774843,
						"collisionPoly": {
							"points": [
								0.3277777777777778,
								0.3277777777777778,
								0.5,
								0.37407407407407406,
								0.7703703703703704,
								0.22777777777777777,
								0.8870370370370371,
								0.5,
								0.6666666666666666,
								0.6666666666666666,
								0.5,
								0.7055555555555556,
								0.43148148148148147,
								0.5666666666666667,
								0.45555555555555555,
								0.5
							]
						},
						"useCollisionPoly": true,
						"duration": 1
					},
					{
						"width": 540,
						"height": 540,
						"originX": 0.5,
						"originY": 0.5,
						"originalSource": "",
						"exportFormat": "png",
						"exportQuality": 0.8,
						"imageSpriteId": 6848297,
						"collisionPoly": {
							"points": [
								0.4351851851851852,
								0.4351851851851852,
								0.5,
								0.024074074074074074,
								0.912962962962963,
								0.08518518518518518,
								0.9351851851851852,
								0.5,
								0.7074074074074074,
								0.7074074074074074,
								0.5,
								0.662962962962963,
								0.47962962962962963,
								0.5185185185185185,
								0.37962962962962965,
								0.5
							]
						},
						"useCollisionPoly": true,
						"duration": 1
					},
					{
						"width": 540,
						"height": 540,
						"originX": 0.5,
						"originY": 0.5,
						"originalSource": "",
						"exportFormat": "png",
						"exportQuality": 0.8,
						"imageSpriteId": 2483589,
						"collisionPoly": {
							"points": [
								0.23703703703703705,
								0.23703703703703705,
								0.5,
								0.11851851851851852,
								0.7777777777777778,
								0.22037037037037038,
								0.6777777777777778,
								0.5,
								0.6537037037037037,
								0.6537037037037037,
								0.5,
								0.6611111111111111,
								0.4185185185185185,
								0.5796296296296296,
								0.30925925925925923,
								0.5
							]
						},
						"useCollisionPoly": true,
						"duration": 1
					},
					{
						"width": 540,
						"height": 540,
						"originX": 0.5,
						"originY": 0.5,
						"originalSource": "",
						"exportFormat": "png",
						"exportQuality": 0.8,
						"imageSpriteId": 3797882,
						"collisionPoly": {
							"points": [
								0.40370370370370373,
								0.40370370370370373,
								0.5,
								0.1,
								0.7333333333333333,
								0.26481481481481484,
								0.6685185185185185,
								0.5,
								0.6759259259259259,
								0.6759259259259259,
								0.5,
								0.6796296296296296,
								0.4388888888888889,
								0.5592592592592592,
								0.3037037037037037,
								0.5
							]
						},
						"useCollisionPoly": true,
						"duration": 1
					},
					{
						"width": 540,
						"height": 540,
						"originX": 0.5,
						"originY": 0.5,
						"originalSource": "",
						"exportFormat": "png",
						"exportQuality": 0.8,
						"imageSpriteId": 8950098,
						"collisionPoly": {
							"points": [
								0.387037037037037,
								0.387037037037037,
								0.5,
								0.31851851851851853,
								0.75,
								0.24814814814814815,
								0.762962962962963,
								0.5,
								0.6962962962962963,
								0.6962962962962963,
								0.5,
								0.6981481481481482,
								0.43148148148148147,
								0.5666666666666667,
								0.3611111111111111,
								0.5
							]
						},
						"useCollisionPoly": true,
						"duration": 1
					}
				],
				"sid": 620672812504431,
				"name": "Attack 1",
				"isLooping": false,
				"isPingPong": false,
				"repeatCount": 1,
				"repeatTo": 0,
				"speed": 14
			},
			{
				"frames": [
					{
						"width": 540,
						"height": 540,
						"originX": 0.5,
						"originY": 0.5,
						"originalSource": "",
						"exportFormat": "png",
						"exportQuality": 0.8,
						"imageSpriteId": 5883377,
						"collisionPoly": {
							"points": [
								0.387037037037037,
								0.387037037037037,
								0.5,
								0.30185185185185187,
								0.7666666666666667,
								0.23148148148148148,
								0.8018518518518518,
								0.5,
								0.7037037037037037,
								0.7037037037037037,
								0.5,
								0.7,
								0.4222222222222222,
								0.575925925925926,
								0.4962962962962963,
								0.5
							]
						},
						"useCollisionPoly": true,
						"duration": 1
					},
					{
						"width": 540,
						"height": 540,
						"originX": 0.5,
						"originY": 0.5,
						"originalSource": "",
						"exportFormat": "png",
						"exportQuality": 0.8,
						"imageSpriteId": 6268661,
						"collisionPoly": {
							"points": [
								0.3592592592592593,
								0.3592592592592593,
								0.5,
								0.29814814814814816,
								0.8148148148148148,
								0.18333333333333332,
								0.9925925925925926,
								0.5,
								0.7,
								0.7,
								0.5,
								0.7055555555555556,
								0.362962962962963,
								0.6351851851851852,
								0.4444444444444444,
								0.5
							]
						},
						"useCollisionPoly": true,
						"duration": 1
					},
					{
						"width": 540,
						"height": 540,
						"originX": 0.5,
						"originY": 0.5,
						"originalSource": "",
						"exportFormat": "png",
						"exportQuality": 0.8,
						"imageSpriteId": 8889853,
						"collisionPoly": {
							"points": [
								0.37407407407407406,
								0.37407407407407406,
								0.5,
								0.2777777777777778,
								0.7518518518518519,
								0.2462962962962963,
								0.9592592592592593,
								0.5,
								0.6981481481481482,
								0.6981481481481482,
								0.5,
								0.6981481481481482,
								0.3333333333333333,
								0.6648148148148149,
								0.43333333333333335,
								0.5
							]
						},
						"useCollisionPoly": true,
						"duration": 1
					},
					{
						"width": 540,
						"height": 540,
						"originX": 0.5,
						"originY": 0.5,
						"originalSource": "",
						"exportFormat": "png",
						"exportQuality": 0.8,
						"imageSpriteId": 5086909,
						"collisionPoly": {
							"points": [
								0.3851851851851852,
								0.3851851851851852,
								0.5,
								0.42962962962962964,
								0.6888888888888889,
								0.30925925925925923,
								0.6611111111111111,
								0.5,
								0.6962962962962963,
								0.6962962962962963,
								0.5,
								0.6962962962962963,
								0.34629629629629627,
								0.6518518518518519,
								0.4148148148148148,
								0.5
							]
						},
						"useCollisionPoly": true,
						"duration": 1
					},
					{
						"width": 540,
						"height": 540,
						"originX": 0.5,
						"originY": 0.5,
						"originalSource": "",
						"exportFormat": "png",
						"exportQuality": 0.8,
						"imageSpriteId": 7713208,
						"collisionPoly": {
							"points": [
								0.4388888888888889,
								0.4388888888888889,
								0.5,
								0.4351851851851852,
								0.7185185185185186,
								0.2796296296296296,
								0.6851851851851852,
								0.5,
								0.7018518518518518,
								0.7018518518518518,
								0.5,
								0.7018518518518518,
								0.37222222222222223,
								0.6259259259259259,
								0.3962962962962963,
								0.5
							]
						},
						"useCollisionPoly": true,
						"duration": 1
					}
				],
				"sid": 734635567898639,
				"name": "Attack 2",
				"isLooping": false,
				"isPingPong": false,
				"repeatCount": 1,
				"repeatTo": 0,
				"speed": 14
			}
		],
		"subfolders": []
	}
}